FB2/Author.py
FB2/Chapter.py
FB2/ChapterContent.py
FB2/DocumentInfo.py
FB2/FB2Builder.py
FB2/FictionBook2.py
FB2/Image.py
FB2/TitleInfo.py
FB2/__init__.py
FB2/constants.py
FB2/py.typed
FB2/builders/BuildAuthorName.py
FB2/builders/DocumentInfoBuilder.py
FB2/builders/TitleInfoBuilder.py
FB2/builders/__init__.py
fb2-0.3.2.dist-info/licenses/LICENSE
fb2-0.3.2.dist-info/METADATA
fb2-0.3.2.dist-info/WHEEL
fb2-0.3.2.dist-info/top_level.txt
fb2-0.3.2.dist-info/RECORD
