Metadata-Version: 2.4
Name: FB2
Version: 0.3.2
Summary: A small package for working with FB2 files
Author-email: Ae-Mc <ae_mc@mail.ru>
License-Expression: MIT
Project-URL: Homepage, https://github.com/Ae-Mc/FB2
Project-URL: Repository, https://github.com/Ae-Mc/FB2
Project-URL: Issues, https://github.com/Ae-Mc/FB2/issues
Classifier: Programming Language :: Python :: 3
Classifier: Programming Language :: Python :: 3.10
Classifier: Programming Language :: Python :: 3.11
Classifier: Programming Language :: Python :: 3.12
Classifier: Programming Language :: Python :: 3.13
Classifier: Operating System :: OS Independent
Classifier: Topic :: Utilities
Requires-Python: >=3.10
License-File: LICENSE
Requires-Dist: iso639-lang>=2.6.3
Requires-Dist: pydantic>=2.12.3
Dynamic: license-file
